devopsagent_api/__init__.py
devopsagent_api/_registration.py
devopsagent_api/auth.py
devopsagent_api/exceptions.py
devopsagent_api/models.py
devopsagent_api/data/community-aidevops/2018-05-10/endpoint-rule-set-1.json
devopsagent_api/data/community-aidevops/2018-05-10/paginators-1.json
devopsagent_api/data/community-aidevops/2018-05-10/service-2.json
devopsagent_api/data/community-aidevops/2018-05-10/waiters-2.json
devopsagent_api/data/community-devops-agent/2025-12-09/endpoint-rule-set-1.json
devopsagent_api/data/community-devops-agent/2025-12-09/paginators-1.json
devopsagent_api/data/community-devops-agent/2025-12-09/service-2.json
devopsagent_api/data/community-devops-agent/2025-12-09/waiters-2.json
devopsagent_api/loaders/__init__.py
devopsagent_api/loaders/service_loader.py
devopsagent_api-1.0.3.dist-info/licenses/LICENSE
docs/conf.py
test_venv/bin/jp.py
devopsagent_api-1.0.3.dist-info/METADATA
devopsagent_api-1.0.3.dist-info/WHEEL
devopsagent_api-1.0.3.dist-info/top_level.txt
devopsagent_api-1.0.3.dist-info/RECORD
