Metadata-Version: 2.4
Name: devopsagent-api
Version: 1.0.3
Summary: Python client library for AWS DevOps Agent API using boto3
Home-page: https://github.com/stefansaftic/community-devops-agent
Author: Stefan Saftic
Author-email: Stefan Saftic <stefan.saftic@gmail.com>
Maintainer-email: Stefan Saftic <stefan.saftic@gmail.com>
License-Expression: Apache-2.0
Project-URL: Homepage, https://github.com/stefansaftic/community-devops-agent
Project-URL: Documentation, https://community-devops-agent.readthedocs.io/en/latest/
Project-URL: Repository, https://github.com/stefansaftic/community-devops-agent
Project-URL: Issues, https://github.com/stefansaftic/community-devops-agent/issues
Project-URL: Changelog, https://github.com/stefansaftic/community-devops-agent/blob/main/CHANGELOG.md
Keywords: aws,devops,agent,boto3,api,client
Classifier: Development Status :: 4 - Beta
Classifier: Intended Audience :: Developers
Classifier: Intended Audience :: System Administrators
Classifier: Operating System :: OS Independent
Classifier: Programming Language :: Python :: 3
Classifier: Programming Language :: Python :: 3.8
Classifier: Programming Language :: Python :: 3.9
Classifier: Programming Language :: Python :: 3.10
Classifier: Programming Language :: Python :: 3.11
Classifier: Topic :: Software Development :: Libraries :: Python Modules
Classifier: Topic :: System :: Systems Administration
Requires-Python: >=3.8
License-File: LICENSE
Requires-Dist: boto3>=1.28.0
Requires-Dist: botocore>=1.31.0
Requires-Dist: pydantic>=2.0.0
Requires-Dist: requests>=2.31.0
Requires-Dist: click>=8.1.0
Requires-Dist: python-dateutil>=2.8.2
Requires-Dist: tabulate>=0.9.0
Requires-Dist: PyYAML>=6.0
Provides-Extra: dev
Requires-Dist: pytest>=7.0.0; extra == "dev"
Requires-Dist: pytest-cov>=4.0.0; extra == "dev"
Requires-Dist: pytest-mock>=3.10.0; extra == "dev"
Requires-Dist: black>=22.0.0; extra == "dev"
Requires-Dist: flake8>=5.0.0; extra == "dev"
Requires-Dist: mypy>=1.0.0; extra == "dev"
Requires-Dist: isort>=5.12.0; extra == "dev"
Provides-Extra: docs
Requires-Dist: sphinx>=5.0.0; extra == "docs"
Requires-Dist: sphinx-rtd-theme>=1.2.0; extra == "docs"
Requires-Dist: myst-parser>=0.18.0; extra == "docs"
Dynamic: author
Dynamic: home-page
Dynamic: license-file
Dynamic: requires-python
